carbonplan_forest_offsets/__init__.py
carbonplan_forest_offsets/utils.py
carbonplan_forest_offsets/analysis/allocation.py
carbonplan_forest_offsets/analysis/assign_project_fldtypcd.py
carbonplan_forest_offsets/analysis/project_crediting_error.py
carbonplan_forest_offsets/analysis/rfia.py
carbonplan_forest_offsets/analysis/southern_cascades_ecosection.py
carbonplan_forest_offsets/analysis/summarize_issuance.py
carbonplan_forest_offsets/arbitrage/arbitrage_mesh.py
carbonplan_forest_offsets/arbitrage/prism_arbitrage.py
carbonplan_forest_offsets/data/__init__.py
carbonplan_forest_offsets/data/catalog.yaml
carbonplan_forest_offsets/load/fia.py
carbonplan_forest_offsets/load/geometry.py
carbonplan_forest_offsets/load/issuance.py
carbonplan_forest_offsets/load/project_db.py
carbonplan_forest_offsets/prefect/workflows/carb_geometries.py
carbonplan_forest_offsets-1.2.0.dist-info/LICENSE
carbonplan_forest_offsets-1.2.0.dist-info/METADATA
carbonplan_forest_offsets-1.2.0.dist-info/WHEEL
carbonplan_forest_offsets-1.2.0.dist-info/top_level.txt
carbonplan_forest_offsets-1.2.0.dist-info/RECORD
