Metadata-Version: 2.1
Name: carbonplan-forest-offsets
Version: 1.2.0
Summary: retrospective analysis of complience IFM projects
Home-page: https://github.com/carbonplan/forest-offsets
Maintainer: Joe Hamman
Maintainer-email: joe@carbonplan.org
License: MIT
Keywords: carbon,data,climate
Platform: UNKNOWN
Requires-Python: >=3.7
Requires-Dist: fsspec
Requires-Dist: fuzzywuzzy
Requires-Dist: geopandas
Requires-Dist: intake
Requires-Dist: intake-geopandas
Requires-Dist: intake-excel
Requires-Dist: numpy
Requires-Dist: pandas
Requires-Dist: regionmask
Requires-Dist: shapely
Requires-Dist: statsmodels
Requires-Dist: scikit-learn
Requires-Dist: xarray
